enginefaas/__init__.py
enginefaas/client.py
enginefaas/exception.py
enginefaas/mapper.py
enginefaas/common/abstract_client.py
enginefaas/common/circuit_breaker.py
enginefaas/common/credential.py
enginefaas/common/sign.py
enginefaas/common/exception/__init__.py
enginefaas/common/exception/sdk_exception.py
enginefaas/common/http/__init__.py
enginefaas/common/http/request.py
enginefaas/common/profile/__init__.py
enginefaas/common/profile/client_profile.py
enginefaas/common/profile/http_profile.py
enginefaas-0.0.1.dist-info/METADATA
enginefaas-0.0.1.dist-info/WHEEL
enginefaas-0.0.1.dist-info/top_level.txt
enginefaas-0.0.1.dist-info/RECORD
